{
    "aaditi": "female",
    "aakriti": "female",
    "aanchal": "female",
    "aarthi": "female",
    "aarushi": "female",
    "aastha": "female",
    "aayush": "male",
    "abhi": "male",
    "abhijeet": "male",
    "abhijit": "male",
    "abhilash": "male",
    "abhinav": "male",
    "abhipsa": "female",
    "abhishek": "male",
    "abigael": "female",
    "abirami": "female",
    "abitha": "female",
    "aboli": "female",
    "adah": "female",
    "adarsh": "male",
    "adhira": "female",
    "advaith": "male",
    "afrah": "female",
    "afsana": "female",
    "ailyn": "female",
    "airen": "female",
    "aishwarya": "female",
    "ajai": "male",
    "ajita": "female",
    "akanksha": "female",
    "akhil": "male",
    "akhilesh": "male",
    "akilah": "female",
    "akshat": "male",
    "akshay": "male",
    "akshaya": "female",
    "akshit": "male",
    "akshita": "female",
    "akshith": "male",
    "akua": "female",
    "alekhya": "female",
    "alethea": "female",
    "alisabeth": "female",
    "alita": "female",
    "alkesh": "male",
    "alpa": "female",
    "alpesh": "male",
    "alpita": "female",
    "amaka": "female",
    "amandeep": "male",
    "amarah": "female",
    "amarnath": "male",
    "amarvir": "male",
    "ameet": "male",
    "amey": "male",
    "ameya": "male",
    "amol": "male",
    "amulya": "female",
    "anabell": "female",
    "anant": "male",
    "andromeda": "female",
    "aniket": "male",
    "anilkumar": "male",
    "anindita": "female",
    "anirban": "female",
    "aniruddha": "male",
    "anirudh": "male",
    "anish": "male",
    "anisha": "female",
    "anjelika": "female",
    "ankita": "female",
    "ankith": "male",
    "ankur": "male",
    "ankush": "male",
    "anmol": "female",
    "anoop": "male",
    "anqi": "female",
    "anshita": "female",
    "anshul": "male",
    "anubhav": "male",
    "anudeep": "male",
    "anuj": "male",
    "anup": "male",
    "anurag": "male",
    "apoorva": "female",
    "aqeel": "male",
    "aravind": "male",
    "ariella": "female",
    "arlyn": "female",
    "arnab": "male",
    "ashwin": "male",
    "beckah": "female",
    "bekah": "female",
    "bren": "female",
    "brena": "female",
    "briant": "female",
    "brinn": "female",
    "calen": "male",
    "celine": "female",
    "chaitanya": "male",
    "chintan": "male",
    "chirag": "male",
    "chuckie": "male",
    "chynna": "female",
    "cliona": "female",
    "deepanshu": "male",
    "demetri": "male",
    "demitri": "male",
    "devika": "female",
    "dharmesh": "male",
    "dheeraj": "male",
    "dhruv": "male",
    "dileep": "male",
    "dimitry": "male",
    "dipesh": "male",
    "dominique": "female",
    "eben": "male",
    "elain": "female",
    "elicia": "female",
    "elitsa": "female",
    "elizbeth": "female",
    "ellana": "female",
    "elliana": "female",
    "em": "female",
    "emmette": "female",
    "eswar": "male",
    "evguenia": "female",
    "gaurav": "male",
    "girish": "male",
    "guenther": "male",
    "himanshu": "male",
    "hitesh": "male",
    "iuliia": "female",
    "ivete": "female",
    "jishnu": "male",
    "nimisha": "female",
    "nishant": "male",
    "nishanthi": "female",
    "nitesh": "male",
    "niti": "female",
    "nitima": "female",
    "nitin": "male",
    "nitish": "male",
    "norm": "male",
    "ozge": "female",
    "ozlem": "female",
    "padmaja": "female",
    "padmini": "female",
    "paige": "female",
    "palani": "female",
    "palash": "male",
    "parag": "male",
    "paresh": "male",
    "parik": "female",
    "parita": "female",
    "parris": "female",
    "parth": "male",
    "partha": "male",
    "parthi": "male",
    "phani": "male",
    "piyali": "female",
    "piyush": "male",
    "poornima": "female",
    "poorvi": "female",
    "pouya": "male",
    "prabhu": "female",
    "prachi": "female",
    "pradeepkumar": "male",
    "pradnya": "female",
    "pradyum": "male",
    "pradyumna": "male",
    "prajakta": "female",
    "prajit": "male",
    "prajwal": "male",
    "prakhar": "male",
    "pranali": "female",
    "pranav": "male",
    "pranay": "male",
    "praneeth": "male",
    "pranesh": "male",
    "pranit": "male",
    "pranith": "female",
    "pranjali": "female",
    "prasanna": "male",
    "prashanth": "male",
    "prasid": "male",
    "prasun": "male",
    "prateek": "male",
    "pratham": "male",
    "prathmesh": "male",
    "pratik": "male",
    "pratiksha": "female",
    "pratyus": "female",
    "pratyush": "male",
    "prayag": "male",
    "preetam": "male",
    "preetham": "male",
    "preethi": "female",
    "premnath": "male",
    "prerana": "female",
    "prerna": "female",
    "prernadas": "female",
    "pritesh": "male",
    "priyabrat": "male",
    "priyabrata": "male",
    "priyadarshi": "male",
    "pulkit": "male",
    "puneet": "male",
    "puru": "female",
    "purushottam": "female",
    "pushkar": "female",
    "rachana": "female",
    "rachita": "female",
    "ragesh": "male",
    "raghavendra": "male",
    "raghu": "male",
    "rajarshi": "male",
    "rajat": "male",
    "rajen": "male",
    "rajini": "male",
    "rajul": "female",
    "rajveer": "male",
    "rakshit": "male",
    "ramakrishna": "male",
    "rameez": "male",
    "ramela": "female",
    "ramya": "female",
    "randee": "female",
    "rangarajan": "male",
    "ranjani": "female",
    "ranjita": "female",
    "rashi": "female",
    "ravikanth": "male",
    "ravikumar": "male",
    "ravindra": "male",
    "rayana": "female",
    "rayhan": "male",
    "raza": "male",
    "ripudaman": "male",
    "rishab": "male",
    "rishabh": "male",
    "rishit": "male",
    "rocio": "female",
    "rohit": "male",
    "ronica": "female",
    "ronique": "female",
    "roop": "female",
    "roopa": "female",
    "roz": "female",
    "rupali": "female",
    "rupesh": "male",
    "rushabh": "male",
    "sabita": "female",
    "sabrin": "female",
    "sakshi": "female",
    "salimah": "female",
    "sameena": "female",
    "sammi": "female",
    "sampada": "female",
    "sanath": "male",
    "sandesh": "male",
    "sandip": "male",
    "sandor": "male",
    "sania": "female",
    "sanika": "female",
    "sanjana": "female",
    "saranraj": "male",
    "saravana": "female",
    "saravanan": "male",
    "sargam": "female",
    "satessh": "male",
    "satwik": "male",
    "satyan": "male",
    "satyanarayana": "male",
    "satyendra": "male",
    "saugat": "male",
    "saurabh": "male",
    "saurav": "male",
    "savitha": "female",
    "sayali": "female",
    "scarlet": "female",
    "senthilkumar": "male",
    "seraphina": "female",
    "serene": "female",
    "seshadri": "female",
    "shabeeb": "male",
    "shabeena": "female",
    "shahir": "male",
    "shairah": "female",
    "sharianna": "female",
    "sharika": "female",
    "sharlee": "female",
    "sharmad": "male",
    "sharmaine": "female",
    "sharvari": "female",
    "shashank": "male",
    "shery": "female",
    "sheyda": "female",
    "shina": "female",
    "shipra": "female",
    "shiree": "female",
    "shiri": "female",
    "shishir": "male",
    "shivakar": "male",
    "shivam": "male",
    "shivi": "female",
    "shreesh": "male",
    "shrenik": "male",
    "shreyansh": "male",
    "shreyas": "male",
    "shreyash": "male",
    "shridhar": "male",
    "shrilekha": "female",
    "shriya": "female",
    "shruthi": "female",
    "shubhada": "female",
    "shubham": "male",
    "shyla": "female",
    "sidd": "male",
    "siddhant": "male",
    "siddharth": "male",
    "siddhartha": "male",
    "siddhesh": "male",
    "sidharth": "male",
    "sidhartha": "male",
    "sidhesh": "male",
    "sidra": "female",
    "signy": "female",
    "soumya": "female",
    "sravani": "female",
    "sravanthi": "female",
    "sravanti": "female",
    "sreevatsan": "male",
    "sridhar": "male",
    "srikant": "male",
    "srikar": "male",
    "srinath": "female",
    "subashini": "female",
    "sucharita": "female",
    "suchi": "female",
    "sudeepa": "female",
    "sudheesh": "male",
    "sugandha": "female",
    "sughosh": "male",
    "sujeet": "male",
    "suki": "female",
    "sumana": "female",
    "sumith": "male",
    "summer": "female",
    "sunaina": "female",
    "sunandini": "female",
    "sundeep": "male",
    "suneel": "male",
    "suparna": "female",
    "supreet": "female",
    "supreeth": "male",
    "suprina": "female",
    "supriya": "female",
    "surabhi": "female",
    "surbhi": "female",
    "surendra": "male",
    "sushant": "male",
    "suz": "female",
    "suzzette": "female",
    "swathi": "female",
    "swetha": "female",
    "tacita": "female",
    "tahlia": "female",
    "takshak": "male",
    "talha": "male",
    "tanni": "female",
    "tansy": "female",
    "tanu": "female",
    "tanuka": "female",
    "tanushree": "female",
    "tanvi": "female",
    "tapesh": "male",
    "tarang": "female",
    "tasneem": "female",
    "tasnim": "female",
    "tathagata": "male",
    "tejal": "female",
    "tejasvi": "female",
    "tejaswini": "female",
    "tejbir": "male",
    "theophane": "male",
    "thiago": "male",
    "thunya": "female",
    "tiffiny": "female",
    "tithi": "female",
    "topher": "male",
    "toria": "female",
    "udgeetha": "female",
    "utkarsh": "male",
    "vaibhav": "male",
    "vaishnavi": "female",
    "valisha": "female",
    "vamsi": "male",
    "vani": "female",
    "vanja": "female",
    "vannetta": "female",
    "vanshi": "female",
    "varshith": "male",
    "varun": "male",
    "vasanth": "male",
    "vatsal": "male",
    "vedang": "male",
    "vedant": "male",
    "veerendra": "male",
    "venkata": "male",
    "vidhi": "female",
    "vimala": "female",
    "vinaya": "female",
    "vineel": "male",
    "vineeth": "male",
    "vinny": "male",
    "vipin": "male",
    "viraj": "male",
    "vishakha": "female",
    "vishal": "male",
    "vishesh": "male",
    "vishnu": "amby",
    "wellington": "male",
    "wendolyn": "female",
    "xiaoling": "female",
    "xixi": "female",
    "yahshua": "male",
    "yajaira": "female",
    "yalin": "male",
    "yanli": "female",
    "yasamin": "female",
    "yashas": "male",
    "yashodhan": "male",
    "yashwanth": "male",
    "yasmeen": "female",
    "yasmim": "female",
    "yaswanth": "male",
    "yatin": "male",
    "yatri": "female",
    "yavar": "male",
    "yazeed": "male",
    "yeji": "female",
    "yesha": "female",
    "yewande": "female",
    "yoon": "female",
    "yoora": "female",
    "yulia": "female",
    "yusef": "male",
    "yuvi": "male",
    "yuvraj": "male",
    "zairah": "female",
    "zakiya": "female",
    "zalika": "female",
    "zareen": "female",
    "zubin": "male",
    "влад": "male"
}
